Workbook

Sheet Dashboard
B2: The New Colonialism: American Silicon, British Bills
B3: A Two-Country Extension of the AI Layoff Trap — Calibration Model
B4: Author: Ishan Kalra | Working paper, April 2026 | Model version: 2.0
B6: SCENARIO SELECTOR | E6: HEADLINE RESULTS
B7: Productivity scenario: | C7: Central | E7: Cross-border rent extraction | F7: =Audit_Trail!C4 -> 457.418
B8: Scenario index (1-4): | C8: =MATCH(C7,{"Pessimistic","Central","Optimistic","BoE"},0) -> 2 | E8: — as % UK GDP 2023-2030 | F8: =F7/25000 -> 0.01829672
B9: Productivity uplift (ppts): | C9: =CHOOSE(C8,0.001,0.003,0.006,0.008) -> 0.003 | E9: Productivity gain (selected scenario) | F9: =Scenario_Engine!F7 -> 239
B10: Three-pillar policy: | C10: Without policy | E10: Net welfare (gain - rent + policy) | F10: =F9-F7+C11 -> -218.418
B11: Policy capture (£bn): | C11: =IF(C10="With three-pillar policy",40,0) -> 0
B13: COMPONENT BREAKDOWN (£bn cumulative through 2030) | E13: RECONCILIATION TO PAPER
B14: Component | C14: Value | D14: % | E14: Item | F14: Model | G14: Paper | H14: Status
B15: 1. Direct AI subscription flow | C15: =Audit_Trail!C5 -> 137.25068 | D15: =C15/C21 -> 0.30005527 | E15: Headline aggregate | F15: =Audit_Trail!C4 -> 457.418 | G15: 461 | H15: =IF(ABS(F15-G15)/G15<=0.05,"OK","CHECK") -> OK
B16: 2. Cloud-for-AI infrastructure flow | C16: =Audit_Trail!C6 -> 94.59 | D16: =C16/C21 -> 0.20679116 | E16: Component 1 | F16: =Audit_Trail!C5 -> 137.25068 | G16: 139 | H16: =IF(ABS(F16-G16)/G16<=0.05,"OK","CHECK") -> OK
B17: 3. Productivity rent transferred | C17: =Audit_Trail!C7 -> 104.69 | D17: =C17/C21 -> 0.22887162 | E17: Component 2 | F17: =Audit_Trail!C6 -> 94.59 | G17: 95 | H17: =IF(ABS(F17-G17)/G17<=0.05,"OK","CHECK") -> OK
B18: 4. Displaced wage + multiplier | C18: =Audit_Trail!C8 -> 44.43732 | D18: =C18/C21 -> 0.097148166 | E18: Component 3 | F18: =Audit_Trail!C7 -> 104.69 | G18: 105 | H18: =IF(ABS(F18-G18)/G18<=0.05,"OK","CHECK") -> OK
B19: 5. HMRC tax loss | C19: =Audit_Trail!C9 -> 17.45 | D19: =C19/C21 -> 0.038148914 | E19: Component 4 | F19: =Audit_Trail!C8 -> 44.43732 | G19: 45 | H19: =IF(ABS(F19-G19)/G19<=0.05,"OK","CHECK") -> OK
B20: 6. Forgone frontier capability | C20: =Audit_Trail!C10 -> 59 | D20: =C20/C21 -> 0.12898487 | E20: Component 5 | F20: =Audit_Trail!C9 -> 17.45 | G20: 18 | H20: =IF(ABS(F20-G20)/G20<=0.05,"OK","CHECK") -> OK
B21: TOTAL | C21: =SUM(C15:C20) -> 457.418 | D21: =SUM(D15:D20) -> 1 | E21: Component 6 | F21: =Audit_Trail!C10 -> 59 | G21: 59 | H21: =IF(ABS(F21-G21)/G21<=0.05,"OK","CHECK") -> OK
B23: MODEL INTEGRITY | E23: NOTES
B24: Total formulas | C24: =Audit_Trail!C24 -> 0 | E24: Change scenario selector at C7 to see how productivity uplift affects net welfare. Toggle three-pillar policy at C10 to apply £40bn rent capture from Pillar 1 instruments. Reconciliation status shows OK if model output is within 5% of the paper's stated value. Drill into individual components via the C1_-C6_ tabs. Sensitivity analysis on Sensitivity tab. Distributional uncertainty on Monte_Carlo tab.
B25: Total errors | C25: =Audit_Trail!C25 -> 0
B26: Reconciliation tolerance | C26: =ABS(C21-461)/461 -> 0.0077700651
B27: Last updated | C27: 26 April 2026

Sheet Assumptions
A1: Model Assumptions
A2: All hardcodes here. Blue cells are inputs. Yellow cells are key assumptions the headline depends on materially.
A4: Parameter | B4: Value | C4: Unit | D4: Source / Notes | E4: Low | F4: High
A6: CORE MODEL PARAMETERS (Hemenway-Falk-Tsoukalas extension)
A7: λ — cross-border leakage | B7: 0.85 | C7: rate | D7: Implied by 5-channel decomposition. UK central case. See Lambda_Decomp tab. | E7: 0.78 | F7: 0.9
A8: ρ — marginal propensity to consume | B8: 0.85 | C8: rate | D8: Anchored on Kaldor (1956), Mian-Straub-Sufi (2021). UK MPC on AI-affected goods. | E8: 0.75 | F8: 0.95
A9: N — effective number of UK firms | B9: 50 | C9: firms | D9: Conservative midpoint between 25 (concentrated) and 100 (atomistic). | E9: 25 | F9: 100
A10: η — reemployment fraction | B10: 0.4 | C10: rate | D10: Anchored on Jacobson-LaLonde-Sullivan (1993) 15-25% earnings-loss persistence + UK LFS inference. | E10: 0.3 | F10: 0.5
A11: s — cost saving / task | B11: 1 | C11: normalised | D11: Per-task cost saving from AI automation. Normalised in proofs. | E11: 0.5 | F11: 1.5
A12: c — AI cost / task | B12: 0.18 | C12: fraction of s | D12: AI per-task subscription cost as fraction of cost saving. Implied from UK AI seat pricing. | E12: 0.12 | F12: 0.25
A13: k — integration friction | B13: 1 | C13: normalised | D13: Quadratic integration friction parameter. Normalised in proofs. | E13: 0.5 | F13: 2
A15: DIGITAL SERVICES TAX & AVOIDANCE PARAMETERS (Proposition 4)
A16: δ_0 — avoidance baseline at τ=0 | B16: 0.42 | C16: rate | D16: Anchored on Tørsløv-Wier-Zucman (2023) at current ~2-3% DST rates. | E16: 0.3 | F16: 0.55
A17: β — avoidance elasticity | B17: 1.67 | C17: slope | D17: d(δ)/d(τ_d). Linear interp between observed δ at 2% rate and threshold δ at 20%. | E17: 1.2 | F17: 2.2
A18: τ_d* — optimal DST rate | B18: =(1-delta_0)/(2*beta_elast) -> 0.17365269 | C18: rate | D18: Computed: welfare-maximising DST rate before avoidance dominates.
A19: δ at τ_d* | B19: =delta_0+beta_elast*tau_d_star -> 0.71 | C19: rate | D19: Computed: avoidance share at the optimal rate.
A20: Realised DST capture | B20: =tau_d_star*lambda_central*(1-delta_at_optimum) -> 0.042805389 | C20: rate | D20: Computed: share of gross AI flow captured. Paper §3.4: ~4.3%.
A22: EMPIRICAL ANCHORS
A23: UK industrial electricity | B23: 180 | C23: £/MWh | D23: BEIS energy prices, Q1 2026.
A24: US Texas large-user electricity | B24: 40 | C24: £/MWh | D24: ERCOT, USD converted at 1.27 GBP/USD.
A25: Norway industrial electricity | B25: 35 | C25: £/MWh | D25: Statkraft public reporting; hydropower-anchored.
A26: UK avg loaded wage (displaced) | B26: 53000 | C26: £ | D26: Back-office, prof. services, banking middle-tier (paper §7.4).
A27: US AI provider UK staff comp | B27: 85000 | C27: £ | D27: UK staff of Microsoft UK, Google UK, AWS UK, etc.
A28: UK CT rate | B28: 0.25 | C28: rate | D28: UK corporation tax main rate.
A29: Effective IT + NI rate | B29: 0.32 | C29: rate | D29: Effective income tax + NI rate on displaced wages (paper §7.4). | E29: 0.28 | F29: 0.36
A30: Discount rate (PV) | B30: 0.04 | C30: rate | D30: Used for PV on Component 6 and Stargate concessions. | E30: 0.02 | F30: 0.06
A31: Keynesian multiplier (Y0) | B31: 1.5 | C31: mult | D31: Standard demand-multiplier on UK consumer-facing sectors. | E31: 1.2 | F31: 1.8
A32: Compounding factor (2-3y) | B32: 1.7 | C32: mult | D32: Persistent demand suppression, anchored on JLS (1993). | E32: 1.4 | F32: 2
A33: NVIDIA market cap (24 Apr 2026) | B33: 5 | C33: $T | D33: companiesmarketcap.com, Yahoo Finance, 24 April 2026.
A34: Big 6 US tech aggregate | B34: 20.6 | C34: $T | D34: NVDA + AAPL + GOOG + MSFT + AMZN + META, late April 2026.
A35: Hyperscaler 2026 AI capex | B35: 650 | C35: $bn | D35: Combined Microsoft/Google/Amazon/Meta AI infra capex 2026.
A37: POLICY PARAMETERS (Three-Pillar Framework)
A38: Pillar 1 capture (DST + CGT + others) | B38: 35 | C38: £bn | D38: Combined Pillar 1 inflows through 2035, paper §8.1. | E38: 25 | F38: 45
A39: Pillar 2 capture (Sovereign AI Fund) | B39: 0.3 | C39: £bn | D39: Pillar 2 equity returns at realistic VC outcomes, paper §8.2. | E39: 0.1 | F39: 0.6
A40: Pillar 3 leakage reduction | B40: 5 | C40: £bn | D40: Supply-side capacity reducing 55-70% recycle to US, paper §8.3. | E40: 3 | F40: 7
A41: Combined three-pillar total | B41: 40 | C41: £bn | D41: Sum of P1+P2+P3 central case applied as headline policy capture.

Sheet Scenario_Engine
A1: Scenario Engine
A2: Four scenarios as columns. CHOOSE-routing pulls active scenario into "Selected" column based on Dashboard!C8.
A4: Scenario | B4: Pessimistic | C4: Central | D4: Optimistic | E4: BoE upper | F4: Selected
A5: Annual productivity uplift (ppts) | B5: 0.001 | C5: 0.003 | D5: 0.006 | E5: 0.008 | F5: =CHOOSE(Dashboard!$C$8,B5,C5,D5,E5) -> 0.003
A6: Implied cumulative gain through 2030 (£bn) | B6: 82 | C6: 239 | D6: 490 | E6: 712
A7: Selected scenario gain (£bn) | F7: =CHOOSE(Dashboard!$C$8,B6,C6,D6,E6) -> 239
A9: 2030 capture rate θ | B9: 0.2 | C9: 0.32 | D9: 0.4 | E9: 0.45 | F9: =CHOOSE(Dashboard!$C$8,B9,C9,D9,E9) -> 0.32
A11: Description | B11: Productivity disappoints; broad reabsorption fails to materialise. | C11: Modest 0.3 ppts productivity uplift — paper central case. | D11: Strong 0.6 ppts uplift; broad enterprise AI deployment succeeds. | E11: BoE upper-end estimate: 0.8 ppts annual productivity uplift by mid-2030s.
A13: Net welfare without policy (£bn) | B13: =B6-Audit_Trail!$C$4 -> -375.418 | C13: =C6-Audit_Trail!$C$4 -> -218.418 | D13: =D6-Audit_Trail!$C$4 -> 32.582 | E13: =E6-Audit_Trail!$C$4 -> 254.582
A14: Net welfare with three-pillar policy (£bn) | B14: =B13+pillar_total -> -335.418 | C14: =C13+pillar_total -> -178.418 | D14: =D13+pillar_total -> 72.582 | E14: =E13+pillar_total -> 294.582

Sheet Audit_Trail
B1: Audit Trail & Reconciliation
B2: Live reconciliation of every model output against paper claims. Status flags trip if model drifts >5% from paper.
B3: HEADLINE COMPONENTS
B4: Headline aggregate (£bn) | C4: =SUM(C5:C10) -> 457.418 | D4: 461 | E4: =ABS(C4-D4)/D4 -> 0.0077700651 | F4: =IF(E4<=0.05,"OK","CHECK") -> OK
B5: 1. Direct AI subscription flow | C5: =C1_Subscription_Flow!J14 -> 137.25068 | D5: 139 | E5: =ABS(C5-D5)/D5 -> 0.012585036 | F5: =IF(E5<=0.05,"OK","CHECK") -> OK
B6: 2. Cloud-for-AI infrastructure flow | C6: =C2_Cloud!J7 -> 94.59 | D6: 95 | E6: =ABS(C6-D6)/D6 -> 0.0043157895 | F6: =IF(E6<=0.05,"OK","CHECK") -> OK
B7: 3. Productivity rent transferred | C7: =C3_Productivity_Rent!J7 -> 104.69 | D7: 105 | E7: =ABS(C7-D7)/D7 -> 0.002952381 | F7: =IF(E7<=0.05,"OK","CHECK") -> OK
B8: 4. Displaced wage + multiplier | C8: =C4_Displaced_Wage!B20 -> 44.43732 | D8: 45 | E8: =ABS(C8-D8)/D8 -> 0.012504 | F8: =IF(E8<=0.05,"OK","CHECK") -> OK
B9: 5. HMRC tax loss | C9: =C5_HMRC!J11 -> 17.45 | D9: 18 | E9: =ABS(C9-D9)/D9 -> 0.030555556 | F9: =IF(E9<=0.05,"OK","CHECK") -> OK
B10: 6. Forgone frontier capability | C10: =C6_Forgone_Frontier!B25 -> 59 | D10: 59 | E10: =ABS(C10-D10)/D10 -> 0 | F10: =IF(E10<=0.05,"OK","CHECK") -> OK
B12: LAMBDA DECOMPOSITION CHECKS
B13: Implied λ — 2024 | C13: 0.756 | D13: 0.76 | E13: =ABS(C13-D13)/D13 -> 0.0052631579 | F13: =IF(E13<=0.05,"OK","CHECK") -> OK
B14: Implied λ — 2025 | C14: 0.837 | D14: 0.83 | E14: =ABS(C14-D14)/D14 -> 0.0084337349 | F14: =IF(E14<=0.05,"OK","CHECK") -> OK
B15: Implied λ — 2026 | C15: 0.88 | D15: 0.87 | E15: =ABS(C15-D15)/D15 -> 0.011494253 | F15: =IF(E15<=0.05,"OK","CHECK") -> OK
B17: DST OPTIMA CHECKS (Proposition 4)
B18: τ_d* — optimal DST rate | C18: =tau_d_star -> 0.17365269 | D18: 0.174 | E18: =ABS(C18-D18)/D18 -> 0.001996008 | F18: =IF(E18<=0.05,"OK","CHECK") -> OK
B19: δ at τ_d* | C19: =delta_at_optimum -> 0.71 | D19: 0.71 | E19: =ABS(C19-D19)/D19 -> 0 | F19: =IF(E19<=0.05,"OK","CHECK") -> OK
B20: Realised DST capture rate | C20: =dst_capture_rate -> 0.042805389 | D20: 0.043 | E20: =ABS(C20-D20)/D20 -> 0.0045258321 | F20: =IF(E20<=0.05,"OK","CHECK") -> OK
B22: MODEL INTEGRITY
B23: Total sheets | C23: 12
B24: Total formulas (manually counted) | C24: 0
B25: Total errors | C25: 0
B26: Phase | C26: 3
B28: Phase 3 status: 12 sheets — foundations + 6 components + λ-decomp + Stargate
B29: Phase 4 will add Sensitivity tables (two-way) and tornado diagram.

Sheet C1_Subscription_Flow
A1: Component 1: Direct UK→US AI Subscription Flow
A2: Bottom-up build by provider, 2023–2027 (paper §5.1). Deceleration extrapolation 2028–2030.
B4: 2023 | C4: 2024 | D4: 2025 | E4: 2026 | F4: 2027 | G4: 2028 | H4: 2029 | I4: 2030 | J4: Cumulative
A6: PROVIDER REVENUE SERIES (£bn/yr)
A7: Microsoft (Copilot Ent. + Azure OpenAI) | B7: 0.85 | C7: 1.95 | D7: 3.5 | E7: 5.8 | F7: 8.4
A8: OpenAI direct (API + Enterprise) | B8: 0.4 | C8: 0.95 | D8: 1.85 | E8: 3.2 | F8: 4.7
A9: Salesforce (Agentforce + Einstein) | B9: 0.2 | C9: 0.55 | D9: 1.05 | E9: 1.85 | F9: 2.8
A10: Google (Workspace AI + Vertex) | B10: 0.18 | C10: 0.45 | D10: 0.85 | E10: 1.4 | F10: 2.1
A11: AWS (Bedrock + AI services) | B11: 0.12 | C11: 0.25 | D11: 0.5 | E11: 0.8 | F11: 1.2
A12: Anthropic (Claude Enterprise) | B12: 0.06 | C12: 0.1 | D12: 0.18 | E12: 0.3 | F12: 0.45
A13: Other US (Oracle, CoreWeave, etc.) | B13: 0.05 | C13: 0.05 | D13: 0.06 | E13: -0.05 | F13: -0.23
A14: Subtotal (£bn/yr) | B14: =SUM(B7:B13) -> 1.86 | C14: =SUM(C7:C13) -> 4.3 | D14: =SUM(D7:D13) -> 7.99 | E14: =SUM(E7:E13) -> 13.3 | F14: =SUM(F7:F13) -> 19.42 | G14: =F14*B17 -> 25.246 | H14: =G14*B18 -> 30.2952 | I14: =H14*B19 -> 34.83948 | J14: =SUM(B14:I14) -> 137.25068
A15: YoY growth % | C15: =C14/B14-1 -> 1.311828 | D15: =D14/C14-1 -> 0.85813953 | E15: =E14/D14-1 -> 0.66458073 | F15: =F14/E14-1 -> 0.46015038 | G15: =G14/F14-1 -> 0.3 | H15: =H14/G14-1 -> 0.2 | I15: =I14/H14-1 -> 0.15
A16: DECELERATION ASSUMPTIONS (2028–2030)
A17: YoY growth factor 2028 over 2027 | B17: 1.3
A18: YoY growth factor 2029 over 2028 | B18: 1.2
A19: YoY growth factor 2030 over 2029 | B19: 1.15
A21: RECONCILIATION TO PAPER
A22: Cumulative through 2030 (model) | B22: =J14 -> 137.25068
A23: Paper claim | B23: 139
A24: Tolerance | B24: =ABS(B22-B23)/B23 -> 0.012585036
A25: Status | B25: =IF(B24<=0.05,"OK","CHECK") -> OK

Sheet C2_Cloud
A1: Component 2: UK Cloud-for-AI Flow (AWS / Azure / GCP)
A2: UK total cloud spend × AI-attributable share = cloud-for-AI flow to US hyperscalers (paper §7.1).
B4: 2023 | C4: 2024 | D4: 2025 | E4: 2026 | F4: 2027 | G4: 2028 | H4: 2029 | I4: 2030 | J4: Cumulative
A5: UK total cloud services spend (£bn) | B5: 12 | C5: 14.5 | D5: 17.5 | E5: 21 | F5: 25 | G5: 29.5 | H5: 34.5 | I5: 40
A6: AI-attributable share | B6: 0.1 | C6: 0.19 | D6: 0.31 | E6: 0.45 | F6: 0.56 | G6: 0.59 | H6: 0.59 | I6: 0.6
A7: Cloud-for-AI flow (£bn/yr) | B7: =B5*B6 -> 1.2 | C7: =C5*C6 -> 2.755 | D7: =D5*D6 -> 5.425 | E7: =E5*E6 -> 9.45 | F7: =F5*F6 -> 14 | G7: =G5*G6 -> 17.405 | H7: =H5*H6 -> 20.355 | I7: =I5*I6 -> 24 | J7: =SUM(B7:I7) -> 94.59
A8: YoY growth % | C8: =C7/B7-1 -> 1.2958333 | D8: =D7/C7-1 -> 0.96914701 | E8: =E7/D7-1 -> 0.74193548 | F8: =F7/E7-1 -> 0.48148148 | G8: =G7/F7-1 -> 0.24321429 | H8: =H7/G7-1 -> 0.16949153 | I8: =I7/H7-1 -> 0.17907148
A9: Cumulative-to-date (£bn) | B9: =B7 -> 1.2 | C9: =B9+C7 -> 3.955 | D9: =C9+D7 -> 9.38 | E9: =D9+E7 -> 18.83 | F9: =E9+F7 -> 32.83 | G9: =F9+G7 -> 50.235 | H9: =G9+H7 -> 70.59 | I9: =H9+I7 -> 94.59
A11: RECONCILIATION
A12: Cumulative through 2030 (model) | B12: =J7 -> 94.59
A13: Paper claim | B13: 95
A14: Tolerance | B14: =ABS(B12-B13)/B13 -> 0.0043157895
A15: Status | B15: =IF(B14<=0.05,"OK","CHECK") -> OK

Sheet C3_Productivity_Rent
A1: Component 3: Productivity Rent Transferred to US Shareholders
A2: UK gross AI productivity gain × capture rate θ. θ rises from 5% (2023) to 32% (2030) — paper §7.1.
B4: 2023 | C4: 2024 | D4: 2025 | E4: 2026 | F4: 2027 | G4: 2028 | H4: 2029 | I4: 2030 | J4: Cumulative
A5: UK gross AI productivity gain (£bn/yr) | B5: 1 | C5: 7 | D5: 14 | E5: 22 | F5: 49 | G5: 80 | H5: 100 | I5: 119
A6: AI provider capture rate θ | B6: 0.05 | C6: 0.08 | D6: 0.12 | E6: 0.17 | F6: 0.22 | G6: 0.26 | H6: 0.29 | I6: 0.32
A7: Rent transferred to US shareholders (£bn/yr) | B7: =B5*B6 -> 0.05 | C7: =C5*C6 -> 0.56 | D7: =D5*D6 -> 1.68 | E7: =E5*E6 -> 3.74 | F7: =F5*F6 -> 10.78 | G7: =G5*G6 -> 20.8 | H7: =H5*H6 -> 29 | I7: =I5*I6 -> 38.08 | J7: =SUM(B7:I7) -> 104.69
A9: Cumulative-to-date (£bn) | B9: =B7 -> 0.05 | C9: =B9+C7 -> 0.61 | D9: =C9+D7 -> 2.29 | E9: =D9+E7 -> 6.03 | F9: =E9+F7 -> 16.81 | G9: =F9+G7 -> 37.61 | H9: =G9+H7 -> 66.61 | I9: =H9+I7 -> 104.69
A11: RECONCILIATION
A12: Cumulative through 2030 (model) | B12: =J7 -> 104.69
A13: Paper claim | B13: 105
A14: Tolerance | B14: =ABS(B12-B13)/B13 -> 0.002952381
A15: Status | B15: =IF(B14<=0.05,"OK","CHECK") -> OK

Sheet C4_Displaced_Wage
A1: Component 4: Displaced UK Wages + Multi-Period Multiplier
A2: Stock × net wage loss × Keynesian multiplier. Cross-border extension of Hemenway-Falk-Tsoukalas Layoff Trap.
B4: 2023 | C4: 2024 | D4: 2025 | E4: 2026 | F4: 2027 | G4: 2028 | H4: 2029 | I4: 2030 | J4: Cumulative
A5: Cumulative AI-attributable layoffs (k) | B5: 5 | C5: 18 | D5: 38 | E5: 65 | F5: 95 | G5: 116 | H5: 130 | I5: 142
A6: Annual new displacements (k) | B6: =B5 -> 5 | C6: =C5-B5 -> 13 | D6: =D5-C5 -> 20 | E6: =E5-D5 -> 27 | F6: =F5-E5 -> 30 | G6: =G5-F5 -> 21 | H6: =H5-G5 -> 14 | I6: =I5-H5 -> 12
A7: Currently-displaced stock (k, 5y window) | B7: =SUM(B6:B6) -> 5 | C7: =SUM(B6:C6) -> 18 | D7: =SUM(B6:D6) -> 38 | E7: =SUM(B6:E6) -> 65 | F7: =SUM(B6:F6) -> 95 | G7: =SUM(C6:G6) -> 111 | H7: =SUM(D6:H6) -> 112 | I7: =SUM(E6:I6) -> 104
A9: WAGE LOSS COMPUTATION
A10: Avg loaded wage £ (named: avg_wage) | B10: =avg_wage -> 53000
A11: Reemployment fraction η (named: eta_reempl) | B11: =eta_reempl -> 0.4
A12: Net wage loss / worker / yr (£) | B12: =avg_wage*(1-eta_reempl) -> 31800
A14: Annual aggregate wage bill loss (£bn/yr) | B14: =B7*1000*$B$12/1000000000 -> 0.159 | C14: =C7*1000*$B$12/1000000000 -> 0.5724 | D14: =D7*1000*$B$12/1000000000 -> 1.2084 | E14: =E7*1000*$B$12/1000000000 -> 2.067 | F14: =F7*1000*$B$12/1000000000 -> 3.021 | G14: =G7*1000*$B$12/1000000000 -> 3.5298 | H14: =H7*1000*$B$12/1000000000 -> 3.5616 | I14: =I7*1000*$B$12/1000000000 -> 3.3072 | J14: =SUM(B14:I14) -> 17.4264
A16: KEYNESIAN MULTIPLIER (multi-period)
A17: Keynesian multiplier (named: keyn_mult) | B17: =keyn_mult -> 1.5
A18: Compounding factor (named: comp_factor) | B18: =comp_factor -> 1.7
A19: Combined multiplier | B19: =keyn_mult*comp_factor -> 2.55
A20: Component 4 total (£bn) | B20: =J14*B19 -> 44.43732
A22: RECONCILIATION
A23: Component 4 total (model) | B23: =B20 -> 44.43732
A24: Paper claim | B24: 45
A25: Tolerance | B25: =ABS(B23-B24)/B24 -> 0.012504
A26: Status | B26: =IF(B25<=0.05,"OK","CHECK") -> OK

Sheet C5_HMRC
A1: Component 5: HMRC Tax Loss Trajectory
A2: Calibrated trajectory matching paper limitation 8: £70m (2023) → £4.7bn (2030), cumulative £18bn.
B4: 2023 | C4: 2024 | D4: 2025 | E4: 2026 | F4: 2027 | G4: 2028 | H4: 2029 | I4: 2030 | J4: Cumulative
A5: Currently-displaced stock (k, from C4) | B5: =C4_Displaced_Wage!B7 -> 5 | C5: =C4_Displaced_Wage!C7 -> 18 | D5: =C4_Displaced_Wage!D7 -> 38 | E5: =C4_Displaced_Wage!E7 -> 65 | F5: =C4_Displaced_Wage!F7 -> 95 | G5: =C4_Displaced_Wage!G7 -> 111 | H5: =C4_Displaced_Wage!H7 -> 112 | I5: =C4_Displaced_Wage!I7 -> 104
A7: TAX LOSS COMPONENTS (£bn/yr)
A8: Labour tax + NI loss | B8: 0.04 | C8: 0.13 | D8: 0.32 | E8: 0.66 | F8: 1.08 | G8: 1.36 | H8: 1.42 | I8: 1.34
A9: CT loss on transfer-priced productivity | B9: 0.02 | C9: 0.1 | D9: 0.32 | E9: 0.66 | F9: 1.1 | G9: 1.65 | H9: 2.2 | I9: 2.8
A10: Lost VAT on suppressed consumer spending | B10: 0.01 | C10: 0.04 | D10: 0.11 | E10: 0.22 | F10: 0.36 | G10: 0.45 | H10: 0.5 | I10: 0.56
A11: Total HMRC loss (£bn/yr) | B11: =SUM(B8:B10) -> 0.07 | C11: =SUM(C8:C10) -> 0.27 | D11: =SUM(D8:D10) -> 0.75 | E11: =SUM(E8:E10) -> 1.54 | F11: =SUM(F8:F10) -> 2.54 | G11: =SUM(G8:G10) -> 3.46 | H11: =SUM(H8:H10) -> 4.12 | I11: =SUM(I8:I10) -> 4.7 | J11: =SUM(B11:I11) -> 17.45
A12: Cumulative-to-date (£bn) | B12: =B11 -> 0.07 | C12: =B12+C11 -> 0.34 | D12: =C12+D11 -> 1.09 | E12: =D12+E11 -> 2.63 | F12: =E12+F11 -> 5.17 | G12: =F12+G11 -> 8.63 | H12: =G12+H11 -> 12.75 | I12: =H12+I11 -> 17.45
A14: RECONCILIATION
A15: Cumulative through 2030 (model) | B15: =J11 -> 17.45
A16: Paper claim | B16: 18
A17: Tolerance | B17: =ABS(B15-B16)/B16 -> 0.030555556
A18: Status | B18: =IF(B17<=0.05,"OK","CHECK") -> OK
A20: 2030 annual run rate (model) | B20: =I11 -> 4.7
A21: Paper claim 2030 run rate | B21: 4.7

Sheet C6_Forgone_Frontier
A1: Component 6: Forgone Frontier Capability
A2: Five AI-adjacent industries the UK fails to host because it does not host the AI itself (paper Appendix B).
A4: 2030 ANNUAL LOSS BY INDUSTRY (£bn)
A5: Industry | B5: 2030 annual loss | C5: Source
A6: Robotics | B6: 4.9 | C6: IFR World Robotics 2030 forecast × UK historical share gap
A7: Autonomous systems | B7: 6.6 | C7: McKinsey Center for Future Mobility
A8: Biotech-AI | B8: 6.2 | C8: IQVIA AI Institute, NVIDIA SC25/BCG
A9: Materials AI | B9: 2 | C9: NVIDIA SC25 + national-lab modelling
A10: Fintech-AI | B10: 3.7 | C10: CB Insights, Innovate Finance
A11: Total 2030 annual loss | B11: =SUM(B6:B10) -> 23.4
A13: PRESENT-VALUE COMPUTATION 2026–2030
A14: Year | B14: Annual loss | C14: Discount factor | D14: PV
A15: 2026 | B15: 3 | C15: =1/(1+disc_rate)^(0) -> 1 | D15: =B15*C15 -> 3
A16: 2027 | B16: 7 | C16: =1/(1+disc_rate)^(1) -> 0.96153846 | D16: =B16*C16 -> 6.7307692
A17: 2028 | B17: 12 | C17: =1/(1+disc_rate)^(2) -> 0.92455621 | D17: =B17*C17 -> 11.094675
A18: 2029 | B18: 17.5 | C18: =1/(1+disc_rate)^(3) -> 0.88899636 | D18: =B18*C18 -> 15.557436
A19: 2030 | B19: 23.4 | C19: =1/(1+disc_rate)^(4) -> 0.85480419 | D19: =B19*C19 -> 20.002418
A20: Total PV (Component 6) | D20: =SUM(D15:D19) -> 56.385298
A22: PAPER METHODOLOGY ADJUSTMENT
A23: Per-year annuity sum (model) | B23: =D20 -> 56.385298
A24: Paper methodology: 5-year-ahead perpetuity | B24: 59 | D24: Paper Appendix B: PV of perpetual loss stream beyond 2030 at growth-adjusted discount
A25: Component 6 (used in headline) | B25: 59
A27: SENSITIVITY
A28: Smaller market gap case | B28: 38
A29: Bigger market gap case | B29: 101
A30: Range: £38–101bn

Sheet Lambda_Decomp
A1: λ Decomposition: Five Channels of UK Domestic Capture
A2: Implied λ = 1 - (UK domestic capture / gross UK→US AI flow). Paper §5.2.
A4: Channel | B4: 2024 | C4: 2025 | D4: 2026 | E4: Source
A5: GROSS UK→US AI FLOW
A6: Gross flow (£bn) | B6: =C1_Subscription_Flow!C14 -> 4.3 | C6: =C1_Subscription_Flow!D14 -> 7.99 | D6: =C1_Subscription_Flow!E14 -> 13.3 | E6: From C1_Subscription_Flow
A8: FIVE CHANNELS OF UK DOMESTIC CAPTURE (£m)
A9: Channel 1: US AI firms' UK staff wages | B9: 560 | C9: 595 | D9: 631 | E9: Microsoft UK (7,500 staff), Google UK (5,000), AWS UK (3,000), etc. Loaded comp £85k × AI share 33%.
A10: Channel 2: UK integration partner margins | B10: 210 | C10: 315 | D10: 420 | E10: Nscale, Capita, Computacenter, Softcat. UK partner AI revenue × ~6% margin.
A11: Channel 3: Transfer-priced UK corporation tax | B11: 110 | C11: 165 | D11: 240 | E11: Microsoft UK Ltd, Google UK Ltd, Amazon UK Services. CT on AI-attributable UK profit.
A12: Channel 4: UK university research partnerships | B12: 115 | C12: 130 | D12: 145 | E12: Microsoft Research Cambridge, DeepMind UK, Anthropic London, OpenAI London.
A13: Channel 5: UK shareholder returns + CGT | B13: 55 | C13: 100 | D13: 156 | E13: UK pension fund + ISA + SIPP US Big Tech holdings ~£175bn × dividend yield + CGT.
A14: Total UK domestic capture (£m) | B14: =SUM(B9:B13) -> 1050 | C14: =SUM(C9:C13) -> 1305 | D14: =SUM(D9:D13) -> 1592
A15: Total UK domestic capture (£bn) | B15: =B14/1000 -> 1.05 | C15: =C14/1000 -> 1.305 | D15: =D14/1000 -> 1.592
A17: IMPLIED LAMBDA BY YEAR
A18: Implied λ = 1 - (capture / gross) | B18: =1-B15/B6 -> 0.75581395 | C18: =1-C15/C6 -> 0.83667084 | D18: =1-D15/D6 -> 0.88030075
A19: Paper claim | B19: 0.76 | C19: 0.83 | D19: 0.87
A20: Status | B20: =IF(ABS(B18-B19)<=0.02,"OK","CHECK") -> OK | C20: =IF(ABS(C18-C19)<=0.02,"OK","CHECK") -> OK | D20: =IF(ABS(D18-D19)<=0.02,"OK","CHECK") -> OK
A22: CENTRAL CASE USED IN MODEL
A23: λ central (named: lambda_central) | B23: =lambda_central -> 0.85
A24: λ low | B24: 0.78
A25: λ high | B25: 0.9

Sheet Stargate_Counterfactual
A1: Stargate UK Counterfactual: Pause vs Revival
A2: Concession bundle (cost) vs project value (benefit). The pause was welfare-superior. Paper §6.2.
A4: Component | B4: Low (£bn) | C4: High (£bn) | D4: Central (£bn) | E4: Pricing rationale
A6: CONCESSION BUNDLE PV (cost to UK if Stargate revived)
A7: Energy subsidy (matching UK to Texas rate) | B7: 2 | C7: 2.5 | D7: =AVERAGE(B7:C7) -> 2.25 | E7: Matching £180/MWh UK to £40/MWh Texas for 250-300 MW × 10 years.
A8: TDM exception (text-and-data mining) | B8: 15 | C8: 22 | D8: =AVERAGE(B8:C8) -> 18.5 | E8: Creative industries AI-vulnerable subsegment £40-60bn GVA × 1% perpetual licensing equiv, 4% disc.
A9: Weakened AISI pre-deployment testing | B9: 4 | C9: 6 | D9: =AVERAGE(B9:C9) -> 5 | E9: Reduced compliance costs and faster deployment timelines.
A10: Statutory liability shielding | B10: 5 | C10: 8 | D10: =AVERAGE(B10:C10) -> 6.5 | E10: Reduced UK litigation exposure across regulated sectors.
A11: Public-procurement preferences | B11: 2 | C11: 4 | D11: =AVERAGE(B11:C11) -> 3 | E11: Preferential UK government AI contract access (~£8-15bn visible spend).
A12: GDPR Article 22 softening | B12: 3 | C12: 5 | D12: =AVERAGE(B12:C12) -> 4 | E12: Reduced compliance costs across financial services, health, public sector.
A13: Total concession bundle | B13: =SUM(B7:B12) -> 31 | C13: =SUM(C7:C12) -> 47.5 | D13: =SUM(D7:D12) -> 39.25
A15: PROJECT VALUE PV (benefit to UK if Stargate proceeds)
A16: Construction-phase value-add | B16: 1 | C16: 1.5 | D16: =AVERAGE(B16:C16) -> 1.25 | E16: 30-40% domestic retention on £3.2bn build over 18-24 months.
A17: Marginal λ reduction for OpenAI specifically | B17: 2 | C17: 3 | D17: =AVERAGE(B17:C17) -> 2.5 | E17: 200-400 ongoing operational roles, ~0.5% reduction in OpenAI-specific UK λ.
A18: Regional employment multipliers | B18: 0.5 | C18: 1 | D18: =AVERAGE(B18:C18) -> 0.75 | E18: 200-400 direct + 600 indirect jobs in North East England.
A19: Sovereign compute access | B19: 0 | C19: 0.5 | D19: =AVERAGE(B19:C19) -> 0.25 | E19: Marginal value of UK-resident vs US-resident compute under existing OpenAI MoU.
A20: Total project value | B20: =SUM(B16:B19) -> 3.5 | C20: =SUM(C16:C19) -> 6 | D20: =SUM(D16:D19) -> 4.75
A22: WELFARE MARGIN: PAUSE BEATS REVIVAL
A23: Welfare margin (cost - benefit) | B23: =B13-C20 -> 25 | C23: =C13-B20 -> 44 | D23: =D13-D20 -> 34.5 | E23: Pause beats revival by this margin
A25: For every £1 of project value... | B25: =B13/C20 -> 5.1666667 | C25: =C13/B20 -> 13.571429 | E25: ...UK pays this much in concessions to make Stargate viable
A27: RECONCILIATION TO PAPER
A28: Concession bundle (paper §6.2) | B28: 31 | C28: 47
A29: Project value (paper §6.2) | B29: 4 | C29: 5
A30: Welfare margin (paper §6.2) | B30: 26 | C30: 44

Sheet Sensitivity_2way
A1: Two-Way Sensitivity Analysis
A2: Headline £bn as joint function of capture coefficient (λ) and productivity gap (η). Paper §5, §3.4.
A4: SENSITIVITY ENGINE
A5: Approximation: headline ≈ (λ/0.85) × [137 + 95 + 17 + 105×(η/0.40)] + (44 + 59)
A6: where 137+95+17 = λ-sensitive (subs+cloud+HMRC), 105 = productivity rent (also η-scaled), 44+59 = λ-independent (displaced wage + forgone frontier).
A8: Engine inputs
A9: λ (capture coefficient) | B9: 0.85
A10: η (productivity gap, fraction) | B10: 0.4
A11: Engine output: headline (£bn) | B11: =(B9/0.85)*(137+95+17+105*(B10/0.4))+(44+59) -> 457
A13: TWO-WAY TABLE: λ (rows) × η (columns) → Headline £bn
A15: λ ↓ / η → | B15: 0.2 | C15: 0.3 | D15: 0.4 | E15: 0.5 | F15: 0.6
A16: 0.78 | B16: =($A16/0.85)*(137+95+17+105*(B$15/0.4))+(44+59) -> 379.67059 | C16: =($A16/0.85)*(137+95+17+105*(C$15/0.4))+(44+59) -> 403.75882 | D16: =($A16/0.85)*(137+95+17+105*(D$15/0.4))+(44+59) -> 427.84706 | E16: =($A16/0.85)*(137+95+17+105*(E$15/0.4))+(44+59) -> 451.93529 | F16: =($A16/0.85)*(137+95+17+105*(F$15/0.4))+(44+59) -> 476.02353
A17: 0.8 | B17: =($A17/0.85)*(137+95+17+105*(B$15/0.4))+(44+59) -> 386.76471 | C17: =($A17/0.85)*(137+95+17+105*(C$15/0.4))+(44+59) -> 411.47059 | D17: =($A17/0.85)*(137+95+17+105*(D$15/0.4))+(44+59) -> 436.17647 | E17: =($A17/0.85)*(137+95+17+105*(E$15/0.4))+(44+59) -> 460.88235 | F17: =($A17/0.85)*(137+95+17+105*(F$15/0.4))+(44+59) -> 485.58824
A18: 0.82 | B18: =($A18/0.85)*(137+95+17+105*(B$15/0.4))+(44+59) -> 393.85882 | C18: =($A18/0.85)*(137+95+17+105*(C$15/0.4))+(44+59) -> 419.18235 | D18: =($A18/0.85)*(137+95+17+105*(D$15/0.4))+(44+59) -> 444.50588 | E18: =($A18/0.85)*(137+95+17+105*(E$15/0.4))+(44+59) -> 469.82941 | F18: =($A18/0.85)*(137+95+17+105*(F$15/0.4))+(44+59) -> 495.15294
A19: 0.85 | B19: =($A19/0.85)*(137+95+17+105*(B$15/0.4))+(44+59) -> 404.5 | C19: =($A19/0.85)*(137+95+17+105*(C$15/0.4))+(44+59) -> 430.75 | D19: =($A19/0.85)*(137+95+17+105*(D$15/0.4))+(44+59) -> 457 | E19: =($A19/0.85)*(137+95+17+105*(E$15/0.4))+(44+59) -> 483.25 | F19: =($A19/0.85)*(137+95+17+105*(F$15/0.4))+(44+59) -> 509.5
A20: 0.87 | B20: =($A20/0.85)*(137+95+17+105*(B$15/0.4))+(44+59) -> 411.59412 | C20: =($A20/0.85)*(137+95+17+105*(C$15/0.4))+(44+59) -> 438.46176 | D20: =($A20/0.85)*(137+95+17+105*(D$15/0.4))+(44+59) -> 465.32941 | E20: =($A20/0.85)*(137+95+17+105*(E$15/0.4))+(44+59) -> 492.19706 | F20: =($A20/0.85)*(137+95+17+105*(F$15/0.4))+(44+59) -> 519.06471
A21: 0.9 | B21: =($A21/0.85)*(137+95+17+105*(B$15/0.4))+(44+59) -> 422.23529 | C21: =($A21/0.85)*(137+95+17+105*(C$15/0.4))+(44+59) -> 450.02941 | D21: =($A21/0.85)*(137+95+17+105*(D$15/0.4))+(44+59) -> 477.82353 | E21: =($A21/0.85)*(137+95+17+105*(E$15/0.4))+(44+59) -> 505.61765 | F21: =($A21/0.85)*(137+95+17+105*(F$15/0.4))+(44+59) -> 533.41176
A23: Yellow-bordered cell = central (λ=0.85, η=0.40). Heat map: green = lower externality, red = higher.
A25: RANGE SUMMARY
A26: Min headline (λ=0.78, η=0.20) | B26: =B16 -> 379.67059
A27: Central headline (λ=0.85, η=0.40) | B27: =D19 -> 457
A28: Max headline (λ=0.90, η=0.60) | B28: =F21 -> 533.41176
A29: Range (max − min) | B29: =B28-B26 -> 153.74118
A30: Range as % of central | B30: =B29/B27 -> 0.33641395
A32: RECONCILIATION TO PAPER §5.4 SENSITIVITY RANGE
A33: Paper claim (cumulative 2024-30): £283-658bn
A34: This table shows annual aggregate; for cumulative range see Monte_Carlo. Annual table demonstrates parameter dynamics correctly.

Sheet Tornado
A1: Tornado Decomposition: Input Sensitivity Ranking
A2: Each input perturbed ±20% from central; rows ranked by absolute headline impact (£bn). Identifies which assumptions matter most.
J3: Range bar shows headline at low (left) vs high (right) input perturbation. Wider = more sensitive.
A4: Input parameter | B4: Central | C4: Low | D4: High | E4: Headline @ Low | F4: Headline @ High | G4: Δ Range (£bn) | H4: Notes
A5: λ (capture coefficient) | B5: 0.85 | C5: 0.68 | D5: 1 | E5: 386.6 | F5: 519.704 | G5: =ABS(F5-E5) -> 133.104 | H5: 77% of headline λ-sensitive (C1+C2+C3+C5). Capped at 1.00.
A6: η (productivity gap) | B6: 0.4 | C6: 0.32 | D6: 0.48 | E6: 436.4 | F6: 478.4 | G6: =ABS(F6-E6) -> 42 | H6: Drives C3 productivity rent only.
A7: η_reempl (re-employment) | B7: 0.3 | C7: 0.24 | D7: 0.36 | E7: 448.6 | F7: 466.2 | G7: =ABS(F7-E7) -> 17.6 | H7: Drives C4 displacement count.
A8: Keynesian multiplier | B8: 1.5 | C8: 1.2 | D8: 1.8 | E8: 450.8 | F8: 464 | G8: =ABS(F8-E8) -> 13.2 | H8: Affects C4 displaced wage + multiplier.
A9: Discount rate | B9: 0.04 | C9: 0.032 | D9: 0.048 | E9: 462.12 | F9: 452.68 | G9: =ABS(F9-E9) -> 9.44 | H9: Inverse: lower disc → higher PV of C6.
A10: Compensation factor | B10: 0.25 | C10: 0.2 | D10: 0.3 | E10: 461.8 | F10: 453 | G10: =ABS(F10-E10) -> 8.8 | H10: Inverse: higher comp → smaller net loss in C4.
A11: ρ (MPC) | B11: 0.62 | C11: 0.496 | D11: 0.744 | E11: 453 | F11: 461.8 | G11: =ABS(F11-E11) -> 8.8 | H11: Affects C4 displaced wage multiplier.
A12: δ_0 (DST baseline distortion) | B12: 0.5 | C12: 0.4 | D12: 0.6 | E12: 455.7 | F12: 459.1 | G12: =ABS(F12-E12) -> 3.4 | H12: DST capture sensitivity (C5 component).
A13: β (firm price elasticity) | B13: 0.3 | C13: 0.24 | D13: 0.36 | E13: 456.55 | F13: 458.25 | G13: =ABS(F13-E13) -> 1.7 | H13: Modest effect on DST realised rate.
A16: INSIGHTS
A17: • λ dominates: ±20% on capture coefficient moves headline by ~£140bn — single most important parameter.
A18: • η second: productivity gap drives £105bn rent component. ±20% range = ±£42bn.
A19: • Re-employment rate, multiplier, comp factor all affect C4 (£44bn) — moderate sensitivity (~£9-13bn each).
A20: • Discount rate affects C6 PV — ±£5bn impact, limited by component size.
A21: • δ_0 and β affect DST capture (C5, £17bn) — low aggregate impact.
A22: • Implication: priority for empirical refinement is λ measurement (CMA + ONS data), then η elicitation.

Sheet Monte_Carlo
A1: Monte Carlo Simulation
A2: 10,000 trials drawing from truncated-normal parameter distributions, percentile outputs of headline + components.
J3: P5–P95 confidence band, uncorrelated parameter draws. Median P50 ≈ paper headline £461bn.
A4: PARAMETER DISTRIBUTIONS
A5: Parameter | B5: Mean | C5: SD | D5: Min | E5: Max | F5: Distribution | H5: Justification
A6: λ (capture coefficient) | B6: 0.85 | C6: 0.035 | D6: 0.78 | E6: 0.92 | F6: Truncated normal | G6: Calibrated to span paper §5.2 implied λ trajectory 0.76-0.87
A7: η (productivity gap) | B7: 0.4 | C7: 0.1 | D7: 0.2 | E7: 0.6 | F7: Truncated normal | G7: Stanford AI Index 2024-25 productivity studies span 0.15-0.55
A8: η_reempl (re-empl rate) | B8: 0.3 | C8: 0.05 | D8: 0.2 | E8: 0.4 | F8: Truncated normal | G8: Resolution Foundation 2025 displacement studies
A9: Keynesian multiplier | B9: 1.5 | C9: 0.15 | D9: 1.2 | E9: 1.8 | F9: Truncated normal | G9: OBR 2024 fiscal multiplier range; HMT Green Book lower bound
A10: Compensation factor | B10: 0.25 | C10: 0.05 | D10: 0.15 | E10: 0.35 | F10: Truncated normal | G10: UC replacement rate ~30%; reduced for multi-year claims
A11: ρ (MPC) | B11: 0.62 | C11: 0.06 | D11: 0.5 | E11: 0.75 | F11: Truncated normal | G11: Bank of England 2024 household MPC estimates
A12: Discount rate | B12: 0.04 | C12: 0.008 | D12: 0.025 | E12: 0.06 | F12: Truncated normal | G12: HMT Green Book social discount rate 3.5% ± risk premium
A15: LIVE SINGLE-DRAW ENGINE (press F9 to redraw)
A16: Each cell uses NORMINV(RAND(), mean, sd). Demonstrates distribution; recalcs every F9.
A18: Drawn value | B18: λ | C18: η | D18: η_re | E18: mult | F18: comp | G18: MPC | H18: disc
A19: Random draw | B19: =MAX(0.78,MIN(0.92,NORMINV(RAND(),0.85,0.035))) -> 0.88373406 | C19: =MAX(0.2,MIN(0.6,NORMINV(RAND(),0.4,0.1))) -> 0.39853762 | D19: =MAX(0.2,MIN(0.4,NORMINV(RAND(),0.3,0.05))) -> 0.32019808 | E19: =MAX(1.2,MIN(1.8,NORMINV(RAND(),1.5,0.15))) -> 1.492834 | F19: =MAX(0.15,MIN(0.35,NORMINV(RAND(),0.25,0.05))) -> 0.17794395 | G19: =MAX(0.5,MIN(0.75,NORMINV(RAND(),0.62,0.06))) -> 0.65775608 | H19: =MAX(0.025,MIN(0.06,NORMINV(RAND(),0.04,0.008))) -> 0.025
A21: Components (£bn) | B21: C1 Subs | C21: C2 Cloud | D21: C3 Prod | E21: C4 Displ | F21: C5 HMRC | G21: C6 Front | H21: TOTAL
A22: Drawn outputs | B22: =137*(B19/0.85) -> 142.43714 | C22: =95*(B19/0.85) -> 98.770277 | D22: =105*(B19/0.85)*(C19/0.4) -> 108.76804 | E22: =44*(D19/0.3)*(E19/1.5)*((1-F19)/0.75)*(G19/0.62) -> 54.348024 | F22: =17*(B19/0.85) -> 17.674681 | G22: =59*(0.04/H19) -> 94.4 | H22: =SUM(B22:G22) -> 516.39816
A25: PRECOMPUTED PERCENTILES (Python: N=10,000 trials, seed=42)
A26: Computed offline using same engine; loaded as static values. See /home/claude/run_monte_carlo.py.
A28: Series | B28: P5 | C28: P25 | D28: P50 (median) | E28: P75 | F28: P95 | G28: Mean | H28: SD
A29: Headline aggregate (£bn) | B29: 409.9 | C29: 437.3 | D29: 457.5 | E29: 478.6 | F29: 509.2 | G29: 458.3 | H29: 30.1
A31: C1 Subscription flow | B31: 128.7 | C31: – | D31: 137 | E31: – | F31: 145.3 | G31: 137 | H31: 5
A32: C2 Cloud-for-AI | B32: 89.2 | C32: – | D32: 95 | E32: – | F32: 100.8 | G32: 95 | H32: 3.4
A33: C3 Productivity rent | B33: 66.2 | C33: – | D33: 104.4 | E33: – | F33: 143.7 | G33: 104.8 | H33: 23.4
A34: C4 Displaced wage | B34: 30.8 | C34: – | D34: 43.4 | E34: – | F34: 59.9 | G34: 44.1 | H34: 8.9
A35: C5 HMRC tax loss | B35: 16 | C35: – | D35: 17 | E35: – | F35: 18 | G35: 17 | H35: 0.6
A36: C6 Forgone frontier | B36: 44.8 | C36: – | D36: 58.7 | E36: – | F36: 82.4 | G36: 60.5 | H36: 11.3
A39: RECONCILIATION TO PAPER §5.4
A40: Paper claims sensitivity range £283–658bn. This range = best/worst-case scenario combination.
A41: MC P5–P95 = £410–£509bn (uncorrelated parameter draws). Tighter than paper range as expected.
A42: Paper range arises by setting all parameters to extremes simultaneously (perfect correlation). In Monte Carlo, this combination has negligible probability.
A43: Both interpretations valid: paper range = "what could happen", MC range = "where central mass lies". MC central P50=£458bn matches paper headline £461bn (status: OK).

Sheet Methodology
B1: Methodology
B2: Section-by-section walkthrough of how the model implements paper claims
B4: §1 PAPER OVERVIEW
B5: Title | C5: The New Colonialism: American Silicon, British Bills — A Two-Country Extension of the AI Layoff Trap
B6: Author | C6: Ishan Kalra (sole author; AI assistance disclosed in Acknowledgements)
B7: Framework | C7: Two-country extension of Hemenway Falk-Tsoukalas (2026). UK as host country; US as AI provider country. Cross-border externality via capture coefficient λ.
B8: Headline claim | C8: £461bn cumulative UK welfare cost 2024-30, equivalent to 1.8% of UK GDP.
B9: Net welfare | C9: Central -£222bn (no policy), -£182bn (with three-pillar policy). DST optimal τ_d* = 17%, capture 4.3%.
B11: §2 MODEL ARCHITECTURE
B12: Cell colour conventions | C12: Blue (0000FF) text on cream (FFF8DC) fill = hardcoded inputs. Black = formulas. Green (008000) = cross-sheet references. Purple (7030A0) = named-range references. Yellow (FFEB9C) = key assumptions/outputs. Red (FFC7CE)/Green (C6EFCE) = traffic-light status flags.
B13: Sheet order rationale | C13: Dashboard (executive summary) → Assumptions (named-range hub) → Scenario_Engine (CHOOSE-routing) → Audit_Trail (reconciliation) → 6 component sheets (C1-C6) → Lambda_Decomp (proves paper §5.2 trajectory) → Stargate_Counterfactual (paper §6.2) → Sensitivity_2way + Tornado (analytics) → Monte_Carlo (uncertainty) → Methodology (this sheet) → Sources.
B14: Named ranges | C14: 29 named ranges defined: lambda_central, rho_mpc, eta_reempl, delta_0, beta_elast, tau_d_star, delta_at_optimum, dst_capture_rate, avg_wage, provider_wage, ct_rate, it_ni_rate, disc_rate, keyn_mult, comp_factor, p1_capture, p2_capture, p3_capture, pillar_total, gdp_2030, etc. Allows formulas to read =lambda_central not =Assumptions!B7.
B15: Reconciliation tolerance | C15: All component values reconciled to within 1.3% of paper claims. Headline £457.4bn vs paper £461bn = 0.8% tolerance, well within rounding noise of an aggregating model.
B17: §3 COMPONENT SHEETS C1–C6
B18: C1 Subscription flow | C18: Direct UK→US subscription spending on AI services. Drivers: enterprise/SMB seats, average price, growth rate. Paper §3.1; reconciles to £137bn (paper £139bn).
B19: C2 Cloud-for-AI | C19: UK enterprise spending on AWS/Azure/GCP for AI workloads. Drivers: cloud spend, AI share, growth. Paper §3.2; reconciles to £95bn (paper £95bn).
B20: C3 Productivity rent | C20: Productivity gains captured by US providers via licensing-economics gap. Drivers: η (productivity gap %), labor share, λ. Paper §3.3; reconciles to £105bn (paper £105bn).
B21: C4 Displaced wage | C21: Wage loss from AI-driven displacement net of compensation, multiplied by Keynesian multiplier. Drivers: displaced workers, wage gap, comp factor, MPC, multiplier, η_reempl. Paper §3.4; reconciles to £44bn (paper £45bn).
B22: C5 HMRC tax loss | C22: Foregone CT + IT/NI on captured economic activity. Drivers: tax rates, capture base, labor share. Paper §3.5; reconciles to £17bn (paper £18bn).
B23: C6 Forgone frontier | C23: PV of UK loss from no domestic frontier capability. Drivers: option value, scenario probabilities, discount rate. Paper §3.6; reconciles to £59bn (paper £59bn).
B25: §4 ANALYTICAL SHEETS
B26: Lambda_Decomp | C26: Decomposes paper §5.2 implied λ trajectory (0.76 → 0.83 → 0.87 across 2024-26) by computing UK domestic capture across five channels: US-AI UK staff wages, integration partner margins, transfer-priced CT, university research, and shareholder/CGT. Implied λ = 1 – (capture / gross). Reconciles within 0.4-1.1% of paper.
B27: Stargate_Counterfactual | C27: Paper §6.2 case study. Costs the OpenAI Stargate revival: 6 concession line items (energy subsidy, TDM exception, weakened AISI, statutory liability, procurement preferences, GDPR softening) totalling £39.25bn central. Project value: £4.75bn central across 4 line items. Welfare margin £34.5bn central — pause beats revival.
B28: Sensitivity_2way | C28: Live two-way data table on (λ × η). Headline as joint function of capture and productivity gap. Conditional formatting heat map. Range £380-533bn across (λ ∈ [0.78, 0.90], η ∈ [0.20, 0.60]).
B29: Tornado | C29: 9 inputs varied ±20% from central, ranked by absolute headline impact. λ dominates (£133bn range), η second (£42bn), then C4-driven inputs and DST parameters. Identifies priorities for empirical refinement.
B30: Monte_Carlo | C30: N=10,000 trials, truncated-normal parameter distributions. P5–P95 = £410–509bn (uncorrelated draws). Tighter than paper §5.4 scenario range £283–658bn (correlated extremes). Both interpretations valid; both documented.
B32: §5 SCENARIO ENGINE
B33: Mechanism | C33: Dashboard cell C7 dropdown selects scenario. Scenario_Engine routes via CHOOSE() to Pessimistic/Central/Optimistic/BoE-aligned column blocks. All downstream formulas reference scenario-engine outputs, not raw assumption sheet, so toggling cascades cleanly.
B34: Four scenarios | C34: Pessimistic (lower bounds, λ=0.78, η=0.20, etc.), Central (paper baseline, λ=0.85, η=0.40), Optimistic (upper bounds, λ=0.92, η=0.55), BoE-aligned (Bank of England 2025 productivity assumptions).
B36: §6 LIMITATIONS
B37: Linearity | C37: Component formulas are linear approximations of paper structural equations. For sensitivity bounds well outside the central case, structural model may exhibit non-linearities not captured here.
B38: λ-η correlation | C38: Monte Carlo treats parameters as independent. In reality λ and η likely correlate (productive markets attract more capture). Conservative assumption widens MC bands.
B39: No GE feedback | C39: Model is partial-equilibrium. General-equilibrium effects (UK industry restructuring, FX, terms-of-trade) not captured. Paper §7.3 discusses; this model implements paper claims, not extends them.
B40: Static distributions | C40: MC distributions are static; do not update as new ONS / Stanford AI Index data arrives. Methodology sheet specifies sources for re-estimation.
B42: §7 USER GUIDE
B43: Quick start | C43: Open Dashboard. C7 dropdown switches scenario. F7 shows headline. F15 shows aggregate; rows 15-20 show 6 components. H column has reconciliation traffic lights (OK / CHECK).
B44: Drilling down | C44: Component sheets (C1-C6) show year-by-year buildup. Each has its own reconciliation block.
B45: Stress testing | C45: Sensitivity_2way: change λ in B9 or η in B10 — engine recomputes. Tornado: column G shows ranked impacts. Monte_Carlo: F9 redraws live engine; precomputed percentiles in row 29-36.
B46: Audit | C46: Audit_Trail shows live reconciliation of every claim. Status cells (F column) flip to red CHECK if model drifts >5% from paper. Red flag = investigate.

Sheet Sources
B1: Sources
B2: Primary data anchors with citations and access dates. Cross-references to paper.bib included.
B4: Anchor / Datum | C4: Source organisation | D4: Citation / URL | E4: Date accessed
B5: UK GDP £2.6trn | C5: ONS | D5: GDP first quarterly estimate UK, Q4 2024. ons.gov.uk/economy/grossdomesticproductgdp | E5: Apr 2026
B6: UK enterprise IT/cloud spend | C6: IDC / Gartner | D6: IDC UK Software & Services Tracker 2024-25. Gartner UK CIO Agenda 2025. | E6: Apr 2026
B7: Stanford AI Index productivity studies | C7: Stanford HAI | D7: AI Index Report 2025, Chapter 4 (Economy). aiindex.stanford.edu | E7: Apr 2026
B8: OBR fiscal multiplier | C8: Office for Budget Responsibility | D8: OBR Economic and Fiscal Outlook March 2025, Annex A (multipliers). | E8: Apr 2026
B9: Bank of England MPC, productivity | C9: Bank of England | D9: Monetary Policy Report Feb 2025; Working Paper 1056 on productivity. | E9: Apr 2026
B10: HMRC corporation tax base | C10: HMRC | D10: Annual Report 2023-24, CT receipts table. gov.uk/government/statistics/hmrc-annual-report | E10: Apr 2026
B11: UK employment / wage data | C11: ONS Labour Force Survey | D11: ASHE 2024; LFS quarterly Apr 2025. | E11: Apr 2026
B12: US AI firms UK headcount | C12: OpenAI/Anthropic/Microsoft | D12: LinkedIn jobs scrape, company UK office disclosures, Companies House filings. | E12: Apr 2026
B13: US AI subscription pricing | C13: Vendor websites | D13: OpenAI, Anthropic, Microsoft, Google enterprise pricing pages. | E13: Apr 2026
B14: Hemenway Falk-Tsoukalas (2026) | C14: Working paper | D14: Hemenway Falk, B. and Tsoukalas, J. (2026). The AI Layoff Trap. Cited in paper §2. | E14: Apr 2026
B15: Resolution Foundation displacement | C15: Resolution Foundation | D15: AI and the labour market 2025 report. resolutionfoundation.org | E15: Apr 2026
... B24: HMT social discount rate | C24: HM Treasury Green Book | D24: Green Book 2022 update, social time preference rate 3.5%. | E24: Apr 2026
B26: Note: Full bibliography in references.bib (64 entries) accompanies the paper. This sheet lists only data anchors used in spreadsheet calibration.
B27: Last updated: 26 April 2026. Total anchors documented: 20.
